Topsis_final/__init__.py
Topsis_final/topsis.py
Topsis_final-1.0.2.dist-info/LICENSE.txt
Topsis_final-1.0.2.dist-info/METADATA
Topsis_final-1.0.2.dist-info/WHEEL
Topsis_final-1.0.2.dist-info/entry_points.txt
Topsis_final-1.0.2.dist-info/top_level.txt
Topsis_final-1.0.2.dist-info/RECORD
